CHANGES
LICENSE
MANIFEST.in
README.rst
setup.py
bin/booger
booger/__init__.py
booger/ui.py
booger.egg-info/PKG-INFO
booger.egg-info/SOURCES.txt
booger.egg-info/dependency_links.txt
booger.egg-info/entry_points.txt
booger.egg-info/requires.txt
booger.egg-info/top_level.txt