Metadata-Version: 1.0
Name: booger
Version: 0.4.3
Summary: Pretty curses-based nose frontend
Home-page: https://github.com/thenoviceoof/booger
Author: thenoviceoof
Author-email: thenoviceoof@gmail.com
License: MIT
Platform: UNKNOWN
